pepperize_cdk_terraform_state_backend/__init__.py
pepperize_cdk_terraform_state_backend/py.typed
pepperize_cdk_terraform_state_backend/_jsii/__init__.py
pepperize_cdk_terraform_state_backend/_jsii/cdk-terraform-state-backend@0.1.1205.jsii.tgz
pepperize_cdk_terraform_state_backend-0.1.1205.dist-info/LICENSE
pepperize_cdk_terraform_state_backend-0.1.1205.dist-info/METADATA
pepperize_cdk_terraform_state_backend-0.1.1205.dist-info/WHEEL
pepperize_cdk_terraform_state_backend-0.1.1205.dist-info/top_level.txt
pepperize_cdk_terraform_state_backend-0.1.1205.dist-info/RECORD
